chardetng_py-0.3.5.dist-info/METADATA
chardetng_py-0.3.5.dist-info/WHEEL
chardetng_py-0.3.5.dist-info/licenses/LICENSE
chardetng_py/__init__.py
chardetng_py/compat.py
chardetng_py/constants.py
chardetng_py/detector.pyi
chardetng_py/detector.pypy39-pp73-ppc_64-linux-gnu.so
chardetng_py/shortcuts.py
chardetng_py-0.3.5.dist-info/RECORD
