Metadata-Version: 2.4
Name: chardetng_py
Version: 0.3.5
Classifier: Programming Language :: Rust
Classifier: Programming Language :: Python :: Implementation :: CPython
Classifier: Programming Language :: Python :: Implementation :: PyPy
License-File: LICENSE
Requires-Python: >=3.9
Project-URL: homepage, https://github.com/john-parton/chardetng-py
Project-URL: documentation, https://chardetng-py.readthedocs.io
Project-URL: changelog, https://github.com/john-parton/chardetng-py/releases
